yta_date/__init__.py
yta_date-0.0.1.dist-info/LICENSE
yta_date-0.0.1.dist-info/METADATA
yta_date-0.0.1.dist-info/WHEEL
yta_date-0.0.1.dist-info/RECORD
